moodify/__init__.py
moodify/player.py
moodify/utils.py
moodify/music_artist/__init__.py
moodify/music_artist/__main__.py
moodify/music_artist/artist.py
moodify/recommender/__init__.py
moodify/recommender/api.py
moodify-1.0.0.dist-info/LICENSE
moodify-1.0.0.dist-info/METADATA
moodify-1.0.0.dist-info/WHEEL
moodify-1.0.0.dist-info/top_level.txt
moodify-1.0.0.dist-info/RECORD
