Metadata-Version: 2.1
Name: moodify
Version: 1.0.0
Summary: A simple Spotify playlist creator that generates custom playlists based on your mood 🎶
Home-page: https://github.com/snowby666/moodify
Author: snowby666
License: UNKNOWN
Keywords: spotify,music,mood,music recommendation,playlist,emotion,api
Platform: UNKNOWN
Classifier: Programming Language :: Python :: 3
Classifier: License :: OSI Approved :: GNU General Public License (GPL)
Classifier: Operating System :: OS Independent
Requires-Python: >=3.7
License-File: LICENSE
Requires-Dist: requests
Requires-Dist: six
Requires-Dist: loguru
Requires-Dist: requests-html
Requires-Dist: bs4
Requires-Dist: ytmusicapi
